titlecap/__init__.py
titlecap/main.py
titlecap/title.py
title_capitalization-0.0.3.dist-info/LICENSE
title_capitalization-0.0.3.dist-info/METADATA
title_capitalization-0.0.3.dist-info/WHEEL
title_capitalization-0.0.3.dist-info/top_level.txt
title_capitalization-0.0.3.dist-info/RECORD
