Metadata-Version: 2.1
Name: title-capitalization
Version: 0.0.3
Summary: A small example package to impose title capitalization upon a string
Home-page: https://github.com/califynic/title-capitalization
Author: Sarah Chen
Author-email: schen21@andover.edu
License: UNKNOWN
Platform: UNKNOWN
Classifier: Programming Language :: Python :: 3
Classifier: License :: OSI Approved :: MIT License
Classifier: Operating System :: OS Independent
Requires-Python: >=3.6
